http_status_check/__init__.py
http_status_check/htpp_status_check.py
http_status_check-0.1.0.dist-info/METADATA
http_status_check-0.1.0.dist-info/WHEEL
http_status_check-0.1.0.dist-info/top_level.txt
http_status_check-0.1.0.dist-info/RECORD
